CVG/__init__.py
CVG/classifiers/__init__.py
CVG/classifiers/bayes.py
CVG/classifiers/knn.py
CVG/clustering/__init__.py
CVG/clustering/hcluster.py
CVG/feature/__init__.py
CVG/feature/feature_point.py
CVG/feature/match.py
CVG/geometry/__init__.py
CVG/geometry/apap.py
CVG/geometry/calculate_homography.py
CVG/geometry/camera.py
CVG/geometry/glabal_homography.py
CVG/geometry/homography.py
CVG/geometry/sfm.py
CVG/geometry/warp.py
CVG/imagesearch/__init__.py
CVG/imagesearch/imagesearch.py
CVG/imagesearch/vocabulary.py
CVG/localdescriptors/__init__.py
CVG/localdescriptors/dsift.py
CVG/localdescriptors/harris.py
CVG/localdescriptors/sift.py
CVG/tools/__init__.py
CVG/tools/blending.py
CVG/tools/camera_calibration.py
CVG/tools/draw.py
CVG/tools/graphcut.py
CVG/tools/image_info.py
CVG/tools/imregistration.py
CVG/tools/imtools.py
CVG/tools/ncut.py
CVG/tools/pca.py
CVG/tools/ransac.py
CVG/tools/rof.py
CVG/tools/system_param.py
CVG-0.2.dist-info/LICENSE
CVG-0.2.dist-info/METADATA
CVG-0.2.dist-info/WHEEL
CVG-0.2.dist-info/top_level.txt
CVG-0.2.dist-info/RECORD
